{
  "generatedAt": "2026-07-04T22:10:51.725Z",
  "candidates": [
    {
      "source": "watch",
      "name": "Grow a Garden 2",
      "ccu": 541097,
      "ageDays": 44.1,
      "rollingAvg": 543667,
      "spikePct": 0,
      "gate": "D:young-chart",
      "verdict": "RED",
      "detail": "both taken, oldest 329.5d (growagarden2.com, growagarden2.net)"
    },
    {
      "source": "discover",
      "name": "[NEW!🔥] Paint Or Seek",
      "ccu": 49464,
      "ageDays": 28.7,
      "rollingAvg": 59509,
      "spikePct": -17,
      "gate": "C:fresh-com",
      "verdict": "RED",
      "detail": "available: paintorseek.net; .com registered 7.1d ago; .com BUILT: \"Paint Or Seek Wiki, Codes, Tier List and Tools\""
    },
    {
      "source": "discover",
      "name": "Clean the Supermarket!",
      "ccu": 45304,
      "ageDays": 19.1,
      "rollingAvg": 47803,
      "spikePct": -5,
      "gate": "C:fresh-com",
      "verdict": "YELLOW",
      "detail": "both taken, oldest 6.9d (cleanthesupermarket.com, cleanthesupermarket.net); .com registered 6.9d ago"
    },
    {
      "source": "discover",
      "name": "Storage Hunters: Open World",
      "ccu": 28741,
      "ageDays": 32.4,
      "rollingAvg": 33932,
      "spikePct": -15,
      "gate": "D:young-chart",
      "verdict": "RED",
      "detail": "both taken, oldest 5689.8d (storagehunters.com, storagehunters.net)"
    },
    {
      "source": "discover",
      "name": "[UPD] Paint My Keyboard! 🎨",
      "ccu": 21442,
      "ageDays": 37.9,
      "rollingAvg": 24248,
      "spikePct": -12,
      "gate": "C:fresh-com",
      "verdict": "YELLOW",
      "detail": "both taken, oldest 8.8d (paintmykeyboard.com, paintmykeyboard.net); .com registered 8.8d ago"
    },
    {
      "source": "discover",
      "name": "[ADMIN ABUSE✨] Anime Fighting Simulator",
      "ccu": 35502,
      "ageDays": 21.2,
      "rollingAvg": 23905,
      "spikePct": 49,
      "gate": "D:young-chart",
      "verdict": "RED",
      "detail": "both taken, oldest 193.4d (animefightingsimulator.com, animefightingsimulator.net)"
    },
    {
      "source": "discover",
      "name": "Animal Hospital (Anomaly) 🧪",
      "ccu": 552527,
      "ageDays": 55.3,
      "rollingAvg": 530657,
      "spikePct": 4,
      "gate": "D:young-chart",
      "verdict": "RED",
      "detail": "both taken, oldest 10488.8d (animalhospital.com, animalhospital.net)"
    },
    {
      "source": "discover",
      "name": "Secure the Airport",
      "ccu": 30154,
      "ageDays": 106.1,
      "rollingAvg": 35089,
      "spikePct": -14,
      "gate": "C:fresh-com",
      "verdict": "RED",
      "detail": "available: securetheairport.net; .com registered 6.4d ago; .com BUILT: \"Secure the Airport Guide &amp; Tools 2026\""
    },
    {
      "source": "discover",
      "name": "Mukbang Game [Testing]",
      "ccu": 64854,
      "ageDays": 93.2,
      "rollingAvg": 70899,
      "spikePct": -9,
      "gate": "C:fresh-com",
      "verdict": "RED",
      "detail": "available: mukbanggame.net; .com registered 9.2d ago; .com BUILT: \"Mukbang Game Wiki, Codes, Tier List and Tools\""
    },
    {
      "source": "discover",
      "name": "[Upd] Clean The Library 📖 ",
      "ccu": 48831,
      "ageDays": 39.1,
      "rollingAvg": 55294,
      "spikePct": -12,
      "gate": "C:fresh-com",
      "verdict": "RED",
      "detail": "both taken, oldest 12.8d (cleanthelibrary.com, cleanthelibrary.net); .com registered 12.8d ago"
    },
    {
      "source": "discover",
      "name": "Build A Soccer Squad! [2X + CODES]",
      "ccu": 44524,
      "ageDays": 31.3,
      "rollingAvg": 39093,
      "spikePct": 14,
      "gate": "C:fresh-com",
      "verdict": "YELLOW",
      "detail": "both taken, oldest 7.1d (buildasoccersquad.com, buildasoccersquad.net); .com registered 7.1d ago"
    },
    {
      "source": "discover",
      "name": "Merge a Nuke!",
      "ccu": 37805,
      "ageDays": 44.4,
      "rollingAvg": 56079,
      "spikePct": -33,
      "gate": "D:young-chart",
      "verdict": "RED",
      "detail": "both taken, oldest 24.2d (mergeanuke.com, mergeanuke.net)"
    },
    {
      "source": "discover",
      "name": "LifeTogether 🏠 RP ",
      "ccu": 51411,
      "ageDays": 1095.1,
      "rollingAvg": 59102,
      "spikePct": -13,
      "gate": "C:fresh-com",
      "verdict": "RED",
      "detail": "available: lifetogetherrp.net; .com registered 5.3d ago; .com BUILT: \"LifeTogether RP Wiki - Codes, Houses, Jobs, Map &amp; Outfit\""
    },
    {
      "source": "discover",
      "name": " [EVENT] 🖌️ Paint To Hide!",
      "ccu": 29112,
      "ageDays": 46.8,
      "rollingAvg": 38004,
      "spikePct": -23,
      "gate": "C:fresh-com",
      "verdict": "RED",
      "detail": "available: painttohide.net; .com registered 0.9d ago; .com BUILT: \"Paint To Hide Wiki — Roblox Codes, Hider &amp; Seeker Guides\""
    },
    {
      "source": "discover",
      "name": "+1 Mine Per Click ⛏️",
      "ccu": 29844,
      "ageDays": 48.9,
      "rollingAvg": 32319,
      "spikePct": -8,
      "gate": "C:fresh-com",
      "verdict": "YELLOW",
      "detail": "both taken, oldest 4.8d (1mineperclick.com, 1mineperclick.net); .com registered 4.8d ago"
    }
  ]
}