{
  "generatedAt": "2026-07-22T10:45:06.099Z",
  "candidates": [
    {
      "source": "discover",
      "name": "[UPD3] Clean the Squishies!",
      "ccu": 20688,
      "ageDays": 28.4,
      "rollingAvg": 25512,
      "spikePct": -19,
      "gate": "C:fresh-com",
      "verdict": "RED",
      "detail": "available: cleanthesquishies.net; .com registered 11.7d ago; .com BUILT: \"Clean the Squishies Route Planner, Codes &amp; Guide\""
    },
    {
      "source": "discover",
      "name": "[⚽SOCCER]🦎 Chameleon!",
      "ccu": 30165,
      "ageDays": 25.9,
      "rollingAvg": 27787,
      "spikePct": 9,
      "gate": "D:young-chart",
      "verdict": "RED",
      "detail": "both taken, oldest 11272.3d (chameleon.com, chameleon.net)"
    },
    {
      "source": "discover",
      "name": "[🏆] Build an ASMR Tower",
      "ccu": 21166,
      "ageDays": 26.7,
      "rollingAvg": 24997,
      "spikePct": -15,
      "gate": "D:young-chart",
      "verdict": "RED",
      "detail": "available: buildanasmrtower.com, buildanasmrtower.net; competitor BUILT: buildanasmrtower.online \"Build an ASMR Tower Guide: How to Play, \", buildanasmrtower.wiki \"Build an ASMR Tower Wiki - Money &amp; B\", build-an-asmr-tower.wiki \"Build an ASMR Tower Wiki - Guides, Codes\" +2 more"
    },
    {
      "source": "discover",
      "name": "[PROMOTIONS] Anime Astral Simulator",
      "ccu": 25939,
      "ageDays": 7.8,
      "rollingAvg": 25345,
      "spikePct": 2,
      "gate": "D:young-chart",
      "verdict": "RED",
      "detail": "available: animeastralsimulator.net; .com BUILT: \"Anime Astral Simulator\""
    },
    {
      "source": "discover",
      "name": "Build A Soccer Squad! [2X]",
      "ccu": 26234,
      "ageDays": 48.9,
      "rollingAvg": 26993,
      "spikePct": -3,
      "gate": "D:young-chart",
      "verdict": "RED",
      "detail": "both taken, oldest 24.6d (buildasoccersquad.com, buildasoccersquad.net)"
    },
    {
      "source": "discover",
      "name": "this awesome game",
      "ccu": 23637,
      "ageDays": 33.6,
      "rollingAvg": 28257,
      "spikePct": -16,
      "gate": "D:young-chart",
      "verdict": "RED",
      "detail": "available: thisawesomegame.com, thisawesomegame.net; competitor BUILT: this-awesome-game.pages.dev \"this awesome game Codes, Guide &amp; Wik\""
    }
  ]
}